<step title="Incoming Request" date="2025-07-09T09:40:45.132" instance="4c1144" url="/api/publish?type=zip" method="POST" type="request" pid="768,1,17" Accept="*/*" Host="soundscribe-backend.scm.azurewebsites.net" User-Agent="AZURECLI/2.66.0 (MSI)" Accept-Encoding="gzip, deflate" Authorization="Bas..." Cache-Control="no-cache" Content-Type="application/octet-stream" Content-Length="4159" x-ms-client-request-id="c356851c-5ca8-11f0-904b-8c1759c91239" x-ms-artifact-checksum="5d92894ebf8245a18b269233494e463edfa91499216003f4c59856af3b036f1f" X-ARR-LOG-ID="c356851c-5ca8-11f0-904b-8c1759c91239" CLIENT-IP="115.87.153.87:54204" X-SITE-DEPLOYMENT-ID="soundscribe-backend" WAS-DEFAULT-HOSTNAME="soundscribe-backend.scm.azurewebsites.net" X-Forwarded-Proto="https" X-AppService-Proto="https" X-Forwarded-TlsVersion="1.3" X-WAWS-Unencoded-URL="/api/publish?type=zip" X-Client-IP="115.87.153.87" X-Client-Port="54204" >
  <step title="Cleanup Xml Logs" date="2025-07-09T09:40:45.136" >
    <step title="Cleanup Infos" date="2025-07-09T09:40:45.156" totalFiles="502" totalCleanup="342" /><!-- duration: 5ms -->
  </step><!-- duration: 30ms -->
  <step title="OneDeploy" date="2025-07-09T09:40:45.179" >
    <step title="Starting PushDeployAsync" date="2025-07-09T09:40:45.187" /><!-- duration: 3ms -->
    <step title="Removing node_modules symlink" date="2025-07-09T09:40:45.197" >
      <step title="Removing _del_node_modules symlink" date="2025-07-09T09:40:45.224" >
        <step title="Writing artifact to /tmp/zipdeploy/14b994ac-0acb-4b32-8346-774b10aef67d.zip" date="2025-07-09T09:40:45.248" >
          <step title="Writing multipart request body to /tmp/zipdeploy/14b994ac-0acb-4b32-8346-774b10aef67d.zip" date="2025-07-09T09:40:45.251" /><!-- duration: 5ms -->
        </step><!-- duration: 13ms -->
        <step title="Removing previous build artifact&apos;s manifest file" date="2025-07-09T09:40:45.272" >
          <step title="Attempting to fetch target branch HEAD" date="2025-07-09T09:40:45.285" /><!-- duration: 3ms -->
          <step title="Acquiring Deployment Lock" date="2025-07-09T09:40:45.292" /><!-- duration: 3ms -->
          <step title="Acquired Deployment Lock" date="2025-07-09T09:40:45.336" /><!-- duration: 4ms -->
          <step title="Performing fetch based deployment" date="2025-07-09T09:40:45.350" >
            <step title="Creating temporary deployment" date="2025-07-09T09:40:45.353" /><!-- duration: 67ms -->
            <step title="Releasing Deployment Lock" date="2025-07-09T09:40:46.608" /><!-- duration: 10ms -->
            <step title="Cleaning up temp folders from previous zip deployments and extracting pushed zip file /tmp/zipdeploy/14b994ac-0acb-4b32-8346-774b10aef67d.zip (0.00 MB) to /tmp/zipdeploy/extracted" date="2025-07-09T09:40:46.642" >
              <step title="ChmodRecursive Process exited with total time taken in ms: 19" date="2025-07-09T09:40:46.668" /><!-- duration: 6ms -->
            </step><!-- duration: 37ms -->
            <step title="None repository commit" date="2025-07-09T09:40:46.685" >
              <step title="Commit id: 63ce7147-4685-4214-be5b-d7a33fc10da4" date="2025-07-09T09:40:46.689" Message="OneDeploy" AuthorName="N/A" AuthorEmail="N/A" /><!-- duration: 4ms -->
            </step><!-- duration: 12ms -->
            <step title="Deployment timer started" date="2025-07-09T09:40:48.702" >
              <step title="DeploymentManager.Deploy(id:63ce7147-4685-4214-be5b-d7a33fc10da4)" date="2025-07-09T09:40:48.715" >
                <step title="Collecting changeset information" date="2025-07-09T09:40:48.734" /><!-- duration: 103ms -->
                <step title="Updating submodules" date="2025-07-09T09:40:48.846" /><!-- duration: 1144ms -->
                <step title="Determining deployment builder" date="2025-07-09T09:40:50.258" >
                  <step title="Builder is OryxBuilder" date="2025-07-09T09:40:50.271" /><!-- duration: 4ms -->
                </step><!-- duration: 21ms -->
                <step title="PreDeployment: context.CleanOutputPath False" date="2025-07-09T09:40:50.329" >
                  <step title="PreDeployment: context.OutputPath /home/site/wwwroot" date="2025-07-09T09:40:50.446" >
                    <step title="Building" date="2025-07-09T09:40:50.591" >
                      <step title="Executing external process" date="2025-07-09T09:40:50.963" type="process" path="bash" arguments="-c &quot;oryx build /tmp/zipdeploy/extracted -o /home/site/wwwroot --platform nodejs --platform-version 18 -p virtualenv_name= --log-file /tmp/build-debug.log  -i /tmp/8ddbeccb0a7a4b7 -p compress_node_modules=tar-gz | tee /tmp/oryx-build.log ; exit $PIPESTATUS &quot;" /><!-- duration: 10029ms -->
                      <step title="Using GenericDeploymentLogParser" date="2025-07-09T09:41:01.377" /><!-- duration: 4ms -->
                      <step title="Modified file to trigger a restart of the app container." date="2025-07-09T09:41:02.704" /><!-- duration: 6ms -->
                      <step title="Skip function trigger and logicapp sync because function is not enabled." date="2025-07-09T09:41:02.714" /><!-- duration: 7ms -->
                      <step title="Purge deployment items" date="2025-07-09T09:41:03.781" >
                        <step title="Remove 97649861-, Success, received at 07/08/2025 18:15:55" date="2025-07-09T09:41:03.874" /><!-- duration: 5ms -->
                      </step><!-- duration: 100ms -->
                    </step><!-- duration: 13366ms -->
                  </step><!-- duration: 13520ms -->
                  <step title="Cleaning up temp files" date="2025-07-09T09:41:03.970" /><!-- duration: 22ms -->
                  <step title="Cleaning up temp files" date="2025-07-09T09:41:03.998" /><!-- duration: 507ms -->
                  <step title="Reloading status file with latest updates" date="2025-07-09T09:41:04.534" >
                    <step title="WebHooksManager.PublishEventAsync: PostDeployment" date="2025-07-09T09:41:04.540" /><!-- duration: 28ms -->
                  </step><!-- duration: 38ms -->
                  <step title="Cleaning up temporary deployment - fetch deployment was successful" date="2025-07-09T09:41:04.580" /><!-- duration: 4ms -->
                </step><!-- duration: 14363ms -->
              </step><!-- duration: 15984ms -->
              <step title="Outgoing response" date="2025-07-09T09:41:04.704" type="response" statusCode="200" statusText="OK" /><!-- duration: 4ms -->
            </step><!-- duration: 16009ms -->
